{
  "properties": [
    {
      "url": "1327-s-colorado-st",
      "type": "Rental",
      "description": {
        "short": "Custom high end 2 bedroom 1.5 bath renovation at a great price! This beautiful home is on a tree-lined block surrounded by new construction homes and walkable to wonderful neighborhood amenities like coffee shops the American Sardine Bar and much more."
      },
      "address": {
        "street": "1327 S Colorado St",
        "city": "Philadelphia",
        "state": "PA",
        "zip": "19146"
      },
      "price": "$1,595",
      "bed": "2",
      "bath": "2",
      "sqft": "1,300",
      "walkscore": "92",
      "image": [
        {
          "title": "",
          "url": "../assets/images/properties/1327_s_colorado_st_philadelphia_pa_19146_picture_01.jpg"
        }
      ]
    },
    {
      "url": "1245-pierce-st",
      "type": "Rental",
      "description": {
        "short": "Custom high end 2 bedroom 1.5 bath renovation at a great price! This beautiful home is on a tree-lined block surrounded by new construction homes and walkable to wonderful neighborhood amenities like coffee shops the American Sardine Bar and much more."
      },
      "address": {
        "street": "1245 Pierce St",
        "city": "Philadelphia",
        "state": "PA",
        "zip": "19148"
      },
      "price": "$1,595",
      "bed": "2",
      "bath": "2",
      "sqft": "1,300",
      "walkscore": "92",
      "image": [
        {
          "title": "",
          "url": "../assets/images/properties/1327_s_colorado_st_philadelphia_pa_19146_picture_01.jpg"
        }
      ]
    }
  ]
}